mitosheet/__init__.py
mitosheet/__main__.py
mitosheet/_frontend.py
mitosheet/_version.py
mitosheet/array_utils.py
mitosheet/column_headers.py
mitosheet/data_in_mito.py
mitosheet/errors.py
mitosheet/excel_utils.py
mitosheet/is_type_utils.py
mitosheet/kernel_utils.py
mitosheet/mito_backend.py
mitosheet/mito_frontend.css
mitosheet/mito_frontend.js
mitosheet/parser.py
mitosheet/save_paths.py
mitosheet/state.py
mitosheet/step.py
mitosheet/steps_manager.py
mitosheet/types.py
mitosheet/utils.py
mitosheet/ai/__init__.py
mitosheet/ai/ai_utils.py
mitosheet/ai/prompt.py
mitosheet/ai/recon.py
mitosheet/api/__init__.py
mitosheet/api/api.py
mitosheet/api/get_ai_completion.py
mitosheet/api/get_available_snowflake_options_and_defaults.py
mitosheet/api/get_code_snippets.py
mitosheet/api/get_column_describe.py
mitosheet/api/get_column_summary_graph.py
mitosheet/api/get_csv_files_metadata.py
mitosheet/api/get_dataframe_as_csv.py
mitosheet/api/get_dataframe_as_excel.py
mitosheet/api/get_defined_df_names.py
mitosheet/api/get_excel_file_metadata.py
mitosheet/api/get_imported_files_and_dataframes_from_analysis_name.py
mitosheet/api/get_imported_files_and_dataframes_from_current_steps.py
mitosheet/api/get_parameterizable_params.py
mitosheet/api/get_params.py
mitosheet/api/get_path_contents.py
mitosheet/api/get_path_join.py
mitosheet/api/get_render_count.py
mitosheet/api/get_split_text_to_columns_preview.py
mitosheet/api/get_test_imports.py
mitosheet/api/get_unique_value_counts.py
mitosheet/api/get_validate_snowflake_credentials.py
mitosheet/code_chunks/__init__.py
mitosheet/code_chunks/add_column_set_formula_code_chunk.py
mitosheet/code_chunks/ai_transformation_code_chunk.py
mitosheet/code_chunks/code_chunk.py
mitosheet/code_chunks/code_chunk_utils.py
mitosheet/code_chunks/column_headers_transform_code_chunk.py
mitosheet/code_chunks/delete_row_code_chunk.py
mitosheet/code_chunks/empty_code_chunk.py
mitosheet/code_chunks/export_to_file_code_chunk.py
mitosheet/code_chunks/melt_code_chunk.py
mitosheet3-0.3.281.dist-info/LICENSE.txt
mitosheet3-0.3.281.dist-info/METADATA
mitosheet3-0.3.281.dist-info/WHEEL
mitosheet3-0.3.281.dist-info/top_level.txt
mitosheet3-0.3.281.dist-info/RECORD
