Metadata-Version: 2.1
Name: mitosheet3
Version: 0.3.281
Summary: The Mito Spreadsheet
Home-page: https://trymito.io
Author: Mito Sheet
Author-email: naterush1997@gmail.com
License: GNU Affero General Public License v3
Keywords: Jupyter,JupyterLab,JupyterLab3
Platform: Linux
Platform: Mac OS X
Platform: Windows
Classifier: License :: OSI Approved :: GNU Affero General Public License v3
Classifier: Programming Language :: Python
Classifier: Programming Language :: Python :: 3
Classifier: Programming Language :: Python :: 3.6
Classifier: Programming Language :: Python :: 3.7
Classifier: Programming Language :: Python :: 3.8
Classifier: Programming Language :: Python :: 3.9
Classifier: Framework :: Jupyter
Requires-Python: >=3.6
Requires-Dist: jupyterlab (~=3.0)
Requires-Dist: pandas (>=0.24.2)
Requires-Dist: analytics-python
Requires-Dist: plotly (>=4.14.3)
Requires-Dist: chardet (>=3.0.4)
Requires-Dist: openpyxl
Requires-Dist: xlsxwriter (<=3.0.2,>=0.6.9)
Provides-Extra: deploy
Requires-Dist: wheel ; extra == 'deploy'
Requires-Dist: twine ; extra == 'deploy'
Requires-Dist: jupyter-packaging (<=0.10.6) ; extra == 'deploy'
Requires-Dist: setuptools (==56.0.0) ; extra == 'deploy'
Provides-Extra: optional_feature_dependencies
Requires-Dist: snowflake-connector-python[pandas] ; (python_version >= "3.7") and extra == 'optional_feature_dependencies'
Provides-Extra: test
Requires-Dist: pytest ; extra == 'test'
Requires-Dist: flake8 ; extra == 'test'
Requires-Dist: types-chardet ; extra == 'test'
Requires-Dist: types-requests ; extra == 'test'
Requires-Dist: mypy ; extra == 'test'
Requires-Dist: pytest-httpserver ; extra == 'test'
